algos/__init__.py
algos/experimentrunners/__init__.py
algos/experimentrunners/exprunner.py
algos/interfaces/__init__.py
algos/interfaces/core_imports.py
algos/interfaces/abstractbaseclasses/__init__.py
algos/interfaces/abstractbaseclasses/component.py
algos/interfaces/abstractbaseclasses/experiment.py
algos/interfaces/abstractbaseclasses/factory.py
algos/interfaces/abstractbaseclasses/hyperparameter.py
algos/interfaces/abstractbaseclasses/io.py
algos/interfaces/baseclasses/__init__.py
algos/interfaces/baseclasses/componentcollection.py
algos/interfaces/metaclasses/__init__.py
algos/interfaces/metaclasses/hyperparameter.py
algos/interfaces/metaclasses/interfacegenerator.py
algos/interfaces/metaclasses/register.py
algos/interfaces/patterns/__init__.py
algos/interfaces/patterns/observersubject.py
algos/interfaces/patterns/singleentity.py
algos/interfaces/patterns/singleton.py
algos/interfaces/utility/__init__.py
algos/interfaces/utility/common.py
algos/interfaces/utility/fileio.py
algos/interfaces/utility/serialisable.py
algos/interfaces/utility/typeddict.py
algos/logger/__init__.py
algos/logger/databaseworker.py
algos/logger/logger.py
algos/logger/proxylogger.py
algos/logger/tables.py
algos/logger/util.py
algos/optimiser/__init__.py
algos/optimiser/experimentrunner.py
algos/optimiser/hpoptimiser.py
algos/optimiser/hyperparameters.py
algos/optimiser/scriptgen.py
algos/optimiser/sftp.py
algos/plotter/__init__.py
algos/plotter/plotter.py
algos/scriptbuilders/__init__.py
algos/scriptbuilders/optimiser.py
algos/scriptbuilders/repeatexperiments.py
algos/scriptbuilders/runexp.py
algos-0.1.0.dist-info/licenses/LICENSE
algos-0.1.0.dist-info/METADATA
algos-0.1.0.dist-info/WHEEL
algos-0.1.0.dist-info/top_level.txt
algos-0.1.0.dist-info/RECORD
