Metadata-Version: 2.4
Name: algos
Version: 0.1.0
Summary: Algorithm OS: An extensible operating system for algorithmic development
Home-page: https://github.com/LlewynS/algos
Author: LlewynS
Author-email: algos251@gmail.com
Classifier: Programming Language :: Python :: 3
Classifier: License :: OSI Approved :: GNU Affero General Public License v3
Classifier: Operating System :: OS Independent
Requires-Python: >=3.10
License-File: LICENSE
Requires-Dist: matplotlib==3.8.2
Requires-Dist: networkx==3.1
Requires-Dist: numpy==1.23.5
Requires-Dist: optuna==4.2.1
Requires-Dist: pandas==1.5.3
Requires-Dist: pexpect==4.8.0
Requires-Dist: psycopg2-binary==2.9.9
Requires-Dist: pysftp==0.2.9
Requires-Dist: pytest==7.2.2
Requires-Dist: PyYAML==6.0.2
Requires-Dist: scikit-learn==1.3.2
Requires-Dist: scipy==1.15.2
Requires-Dist: seaborn==0.13.2
Requires-Dist: setuptools==65.5.0
Requires-Dist: shap==0.46.0
Requires-Dist: SQLAlchemy==2.0.21
Dynamic: author
Dynamic: author-email
Dynamic: classifier
Dynamic: description
Dynamic: description-content-type
Dynamic: home-page
Dynamic: license-file
Dynamic: requires-dist
Dynamic: requires-python
Dynamic: summary
